swh/vault/__init__.py
swh/vault/backend.py
swh/vault/cache.py
swh/vault/cli.py
swh/vault/cooking_tasks.py
swh/vault/exc.py
swh/vault/in_memory_backend.py
swh/vault/interface.py
swh/vault/py.typed
swh/vault/to_disk.py
swh/vault/api/__init__.py
swh/vault/api/client.py
swh/vault/api/serializers.py
swh/vault/api/server.py
swh/vault/cookers/__init__.py
swh/vault/cookers/base.py
swh/vault/cookers/directory.py
swh/vault/cookers/git_bare.py
swh/vault/cookers/revision_flat.py
swh/vault/cookers/revision_gitfast.py
swh/vault/cookers/utils.py
swh/vault/sql/30-schema.sql
swh/vault/sql/upgrades/002.sql
swh/vault/sql/upgrades/003.sql
swh/vault/tests/__init__.py
swh/vault/tests/conftest.py
swh/vault/tests/test_backend.py
swh/vault/tests/test_cache.py
swh/vault/tests/test_cli.py
swh/vault/tests/test_cookers.py
swh/vault/tests/test_cookers_base.py
swh/vault/tests/test_git_bare_cooker.py
swh/vault/tests/test_init_cookers.py
swh/vault/tests/test_server.py
swh/vault/tests/test_to_disk.py
swh/vault/tests/vault_testing.py
swh_vault-2.0.0.dist-info/licenses/AUTHORS
swh_vault-2.0.0.dist-info/licenses/LICENSE
swh_vault-2.0.0.dist-info/METADATA
swh_vault-2.0.0.dist-info/WHEEL
swh_vault-2.0.0.dist-info/entry_points.txt
swh_vault-2.0.0.dist-info/top_level.txt
swh_vault-2.0.0.dist-info/RECORD
